flock_context/__init__.py
flock_context/py.typed
flock_context_manager-1.0.0.dist-info/licenses/LICENSE
flock_context_manager-1.0.0.dist-info/METADATA
flock_context_manager-1.0.0.dist-info/WHEEL
flock_context_manager-1.0.0.dist-info/top_level.txt
flock_context_manager-1.0.0.dist-info/RECORD
