Metadata-Version: 2.4
Name: flock-context-manager
Version: 1.0.0
Summary: A flock implementation using Python's context manager.
Author-email: Joe Pitt <joe.pitt@joepitt.co.uk>
License-Expression: GPL-3.0-only
Project-URL: Source, https://github.com/joepitt91/flock-context-manager
Classifier: Development Status :: 4 - Beta
Classifier: Intended Audience :: Developers
Classifier: Natural Language :: English
Classifier: Operating System :: OS Independent
Classifier: Programming Language :: Python :: 3 :: Only
Classifier: Topic :: Software Development
Classifier: Typing :: Typed
Requires-Python: ~=3.9
License-File: LICENSE
Dynamic: license-file
